rdwv/__init__.py
rdwv/coin.py
rdwv/errors.py
rdwv/event_delivery.py
rdwv/logger.py
rdwv/manager.py
rdwv/py.typed
rdwv/types.py
rdwv/utils.py
rdwv/coins/__init__.py
rdwv/coins/bch.py
rdwv/coins/bnb.py
rdwv/coins/bsty.py
rdwv/coins/btc.py
rdwv/coins/eth.py
rdwv/coins/grs.py
rdwv/coins/ltc.py
rdwv/coins/matic.py
rdwv/coins/sbch.py
rdwv/coins/trx.py
rdwv/coins/xmr.py
rdwv/coins/xrg.py
rdwv/providers/__init__.py
rdwv/providers/jsonrpcrequests.py
rdwv-1.0.dist-info/LICENSE
rdwv-1.0.dist-info/METADATA
rdwv-1.0.dist-info/WHEEL
rdwv-1.0.dist-info/top_level.txt
rdwv-1.0.dist-info/RECORD
