Metadata-Version: 2.1
Name: rdwv
Version: 1.0
Summary: rdwv coins support library
Home-page: https://github.com/rdwv/rdwv-sdk
Author: RDWV
Author-email: admin@rdwv.app
License: MIT
Keywords: electrum,daemon,rdwv
Classifier: Development Status :: 5 - Production/Stable
Classifier: Intended Audience :: Developers
Classifier: Topic :: Software Development :: Build Tools
Classifier: License :: OSI Approved :: MIT License
Classifier: Programming Language :: Python :: 3
Classifier: Programming Language :: Python :: 3.9
Classifier: Programming Language :: Python :: 3.10
Classifier: Programming Language :: Python :: 3.11
Classifier: Programming Language :: Python :: 3.12
Requires-Python: >=3.9
License-File: LICENSE
Requires-Dist: jsonrpcclient
Requires-Dist: aiohttp <4.0.0
Requires-Dist: universalasync
Provides-Extra: proxy
Requires-Dist: aiohttp-socks ; extra == 'proxy'
